{
  "filters": {
    "alphaChains": [],
    "alphaPeriod": 20,
    "alphaRankType": 20,
    "futuresMinuteQuoteVolume": "300000",
    "futuresMinutes": 5,
    "futuresQuoteAsset": "USDT",
    "futuresRequireAllMinutes": true,
    "top10Threshold": "80"
  },
  "generatedAt": "2026-05-26T07:47:25.500652+00:00",
  "generatedAtMs": 1779781645500,
  "localTime": "2026-05-26 15:47:25 CST",
  "matches": [],
  "status": "ok",
  "summary": {
    "freshAlertCount": 0,
    "matchCount": 0,
    "symbols": []
  },
  "telegram": {
    "alertCooldownSeconds": 3600,
    "sendEmptyResult": true
  }
}
